appdaemon/__init__.py
appdaemon/__main__.py
appdaemon/adapi.py
appdaemon/adbase.py
appdaemon/admin.py
appdaemon/admin_loop.py
appdaemon/app_management.py
appdaemon/appdaemon.py
appdaemon/callbacks.py
appdaemon/dashboard.py
appdaemon/dependency.py
appdaemon/dependency_manager.py
appdaemon/entity.py
appdaemon/events.py
appdaemon/exceptions.py
appdaemon/futures.py
appdaemon/http.py
appdaemon/logging.py
appdaemon/parse.py
appdaemon/plugin_management.py
appdaemon/py.typed
appdaemon/pyversions.py
appdaemon/scheduler.py
appdaemon/sequences.py
appdaemon/services.py
appdaemon/state.py
appdaemon/thread_async.py
appdaemon/threads.py
appdaemon/types.py
appdaemon/utility_loop.py
appdaemon/utils.py
appdaemon/version.py
appdaemon/assets/aui/appdaemon.png
appdaemon/assets/aui/favicon.ico
appdaemon/assets/aui/index.html
appdaemon/assets/aui/css/app.css
appdaemon/assets/aui/css/chunk-vendors.css
appdaemon/assets/aui/js/app.js
appdaemon/assets/aui/js/app.js.map
appdaemon/assets/aui/js/chunk-vendors.js
appdaemon/assets/aui/js/chunk-vendors.js.map
appdaemon/assets/css/all.css
appdaemon/assets/css/climacons-font.css
appdaemon/assets/css/fontawesome.min.css
appdaemon/assets/css/fonts.css
appdaemon/assets/css/jquery-ui.css
appdaemon/assets/css/jquery.gridster.css
appdaemon/assets/css/main.css
appdaemon/assets/css/materialdesignicons.min.css
appdaemon/assets/css/non_dashboard.css
appdaemon/assets/css/rickshaw.min.css
appdaemon/assets/css/v4-shims.min.css
appdaemon/assets/css/default/dashboard.css
appdaemon/assets/css/default/variables.yaml
appdaemon/assets/css/glassic/dashboard.css
appdaemon/assets/css/glassic/variables.yaml
appdaemon/assets/css/glassic/img/carbon1.jpg
appdaemon/assets/css/glassic/img/carbon2.jpg
appdaemon/assets/css/glassic/img/carbon3.jpg
appdaemon/assets/css/glassic/img/carbon4.jpg
appdaemon/assets/css/glassic/img/glassic_bg.jpg
appdaemon/assets/css/images/ui-icons_444444_256x240.png
appdaemon/assets/css/images/ui-icons_555555_256x240.png
appdaemon-4.5.13.dist-info/licenses/LICENSE.md
appdaemon-4.5.13.dist-info/METADATA
appdaemon-4.5.13.dist-info/WHEEL
appdaemon-4.5.13.dist-info/entry_points.txt
appdaemon-4.5.13.dist-info/top_level.txt
appdaemon-4.5.13.dist-info/RECORD
