Metadata-Version: 2.4
Name: appdaemon
Version: 4.5.13
Summary: Apps for the Home Assistant home automation package.
Author-email: Andrew I Cockburn <appdaemon@acockburn.com>
Project-URL: documentation, https://appdaemon.readthedocs.io
Project-URL: repository, https://github.com/AppDaemon
Project-URL: changelog, https://github.com/AppDaemon/appdaemon/blob/master/docs/HISTORY.rst
Keywords: appdaemon,home,automation
Classifier: Development Status :: 5 - Production/Stable
Classifier: Intended Audience :: Developers
Classifier: Natural Language :: English
Classifier: Programming Language :: Python :: 3.10
Classifier: Programming Language :: Python :: 3.11
Classifier: Programming Language :: Python :: 3.12
Classifier: Programming Language :: Python :: 3.13
Classifier: Topic :: Home Automation
Classifier: Typing :: Typed
Requires-Python: <3.14,>=3.10
License-File: LICENSE.md
Requires-Dist: importlib-metadata; python_version < "3.8"
Requires-Dist: aiohttp<3.12.0,>=3.9.0
Requires-Dist: aiohttp_jinja2<1.7.0,>=1.5.1
Requires-Dist: astral~=3.2
Requires-Dist: bcrypt<4.3.0,>=4.0.1
Requires-Dist: deepdiff==8.2.0
Requires-Dist: feedparser~=6.0.10
Requires-Dist: iso8601<2.2,>=1.1
Requires-Dist: paho-mqtt<2.2.0,>=1.6.1
Requires-Dist: pid~=3.0.4
Requires-Dist: python-dateutil<2.10.0,>=2.8.2
Requires-Dist: python-socketio<5.12,>=5.5
Requires-Dist: pytz<2025.2.0,>=2022.7.1
Requires-Dist: pyyaml~=6.0.1
Requires-Dist: requests<2.33.0,>=2.28.2
Requires-Dist: sockjs<0.14,>=0.11
Requires-Dist: uvloop==0.21.0; sys_platform != "win32"
Requires-Dist: tomli==2.2.1
Requires-Dist: tomli_w<1.3,>=1.0
Requires-Dist: pydantic~=2.10.6
Provides-Extra: dev
Requires-Dist: build>=1.2.1; extra == "dev"
Requires-Dist: gitpython>=3.1.43; extra == "dev"
Requires-Dist: ipykernel>=6.29.5; extra == "dev"
Requires-Dist: notebook>=7.3.2; extra == "dev"
Requires-Dist: pre-commit>=3.8.0; extra == "dev"
Requires-Dist: pytest>=8.3.2; extra == "dev"
Requires-Dist: pytest-asyncio>=1.0.0; extra == "dev"
Requires-Dist: rich>=13.8.0; extra == "dev"
Requires-Dist: ruff>=0.6.3; extra == "dev"
Provides-Extra: doc
Requires-Dist: myst-parser>=4.0.0; extra == "doc"
Requires-Dist: sphinx-autobuild>=2021.3.14; extra == "doc"
Requires-Dist: sphinx-rtd-theme>=3.0.2; extra == "doc"
Requires-Dist: sphinx-copybutton>=0.5.2; extra == "doc"
Requires-Dist: sphinx-tabs>=3.4.7; extra == "doc"
Requires-Dist: pygments>=2.14; extra == "doc"
Requires-Dist: pytest>=8.3.2; extra == "doc"
Requires-Dist: pytest-asyncio>=1.0.0; extra == "doc"
Dynamic: license-file
